multicall_thread_safe/__init__.py
multicall_thread_safe/call.py
multicall_thread_safe/constants.py
multicall_thread_safe/exceptions.py
multicall_thread_safe/loggers.py
multicall_thread_safe/multicall.py
multicall_thread_safe/signature.py
multicall_thread_safe/utils.py
multicall_thread_safe-0.1.5.dist-info/WHEEL
multicall_thread_safe-0.1.5.dist-info/METADATA
multicall_thread_safe-0.1.5.dist-info/RECORD
