Metadata-Version: 2.1
Name: multicall-thread-safe
Version: 0.1.5
Summary: Thread Safe Multicall for execution in containerised environments, tweaked from https://github.com/banteg/multicall.py
Home-page: https://github.com/cbsystango/multicall-thread-safe/
Author: cbhondwe
Requires-Python: >=3.8,<4.0
Classifier: Programming Language :: Python :: 3
Classifier: Programming Language :: Python :: 3.8
Classifier: Programming Language :: Python :: 3.9
Classifier: Programming Language :: Python :: 3.10
Classifier: Programming Language :: Python :: 3.11
Requires-Dist: black (>=22.8,<23.0)
Requires-Dist: flake8 (>=5.0,<6.0)
Requires-Dist: joblib (>=1.2,<2.0)
Requires-Dist: pytest (>=7.1,<8.0)
Project-URL: Repository, https://github.com/cbsystango/multicall-thread-safe/
